{
  "BMNR": {
    "price": 42.04,
    "day_gain": -1.81,
    "day_gain_pct": -4.1277,
    "market_cap": 9312498370,
    "market_cap_day_gain": -400941934,
    "market_cap_day_gain_pct": -4.305417505177154,
    "basic_shares_outstanding": 184595983,
    "assumed_diluted_shares_outstanding": 221515180
  },
  "ETH": {
    "price": 4262.15,
    "day_gain": -44.83,
    "day_gain_pct": -1.041,
    "market_cap": 514513469440,
    "market_cap_day_gain": -5411751836,
    "market_cap_day_gain_pct": -1.0518192735950505,
    "circulating_supply": 120705152
  },
  "BMNR_ETH": {
    "holdings": 1866974,
    "value": 7957331256.253906,
    "ownership_pct": 1.5467227115541846,
    "goal_progress_pct": 30.93445423108369,
    "average_cost_per_eth": 3957.15235830815,
    "ownership_trend": [
      {
        "date": "2025-07-13",
        "ownership_pct": 0.13514170463908615
      },
      {
        "date": "2025-07-20",
        "ownership_pct": 0.24909293018412337
      },
      {
        "date": "2025-07-27",
        "ownership_pct": 0.46955742203945033
      },
      {
        "date": "2025-08-03",
        "ownership_pct": 0.5177765734473372
      },
      {
        "date": "2025-08-06",
        "ownership_pct": 0.6902215739722527
      },
      {
        "date": "2025-08-11",
        "ownership_pct": 0.9529452396530681
      },
      {
        "date": "2025-08-17",
        "ownership_pct": 1.2620612913026281
      },
      {
        "date": "2025-08-25",
        "ownership_pct": 1.4199054237552344
      },
      {
        "date": "2025-08-28",
        "ownership_pct": 1.4851810136488623
      },
      {
        "date": "2025-09-02",
        "ownership_pct": 1.5467227115541846
      }
    ],
    "weighted_avg_cost_curve": [
      {
        "date": "2025-07-13",
        "weighted_avg_cost": 2794.0662199689805
      },
      {
        "date": "2025-07-20",
        "weighted_avg_cost": 3135.533332446419
      },
      {
        "date": "2025-07-27",
        "weighted_avg_cost": 3371.2144676946964
      },
      {
        "date": "2025-08-03",
        "weighted_avg_cost": 3382.4629021909395
      },
      {
        "date": "2025-08-06",
        "weighted_avg_cost": 3446.181386405292
      },
      {
        "date": "2025-08-11",
        "weighted_avg_cost": 3632.640059499902
      },
      {
        "date": "2025-08-17",
        "weighted_avg_cost": 3807.3760707325127
      },
      {
        "date": "2025-08-25",
        "weighted_avg_cost": 3915.498046851069
      },
      {
        "date": "2025-08-28",
        "weighted_avg_cost": 3942.945700037374
      },
      {
        "date": "2025-09-02",
        "weighted_avg_cost": 3957.15235830815
      }
    ],
    "nav_diluted_history": [
      {
        "date": "2025-07-13",
        "nav_diluted": 3.138635444167486
      },
      {
        "date": "2025-07-20",
        "nav_diluted": 5.785126816739207
      },
      {
        "date": "2025-07-27",
        "nav_diluted": 10.905364645361153
      },
      {
        "date": "2025-08-03",
        "nav_diluted": 12.0252435021556
      },
      {
        "date": "2025-08-06",
        "nav_diluted": 16.030239534005567
      },
      {
        "date": "2025-08-11",
        "nav_diluted": 22.13193709161447
      },
      {
        "date": "2025-08-17",
        "nav_diluted": 29.31108729294922
      },
      {
        "date": "2025-08-25",
        "nav_diluted": 32.97698147485768
      },
      {
        "date": "2025-08-28",
        "nav_diluted": 34.49299224759605
      },
      {
        "date": "2025-09-02",
        "nav_diluted": 35.92228422564045
      }
    ]
  },
  "BMNR_NAV": {
    "eth_value": 7957331256.253906,
    "btc_value": 21136485.0,
    "cash_value": 562000000.0,
    "total_value": 8540467741.253906,
    "nav_per_basic_share_total": 46.265729010105254,
    "nav_per_diluted_share_total": 38.554774175087715
  },
  "derived": {
    "eth_per_basic_share": 0.010113838699451658,
    "eth_per_diluted_share": 0.008428198916209715,
    "eth_value_per_basic_share": 43.10674107076854,
    "eth_value_per_diluted_share": 35.92228422564045,
    "": 0.009863556780746055,
    "nav_basic": 46.265729010105254,
    "nav_diluted": 38.554774175087715,
    "ytd_yield_pct": 248.75,
    "qtd_yield_pct": 0.0
  },
  "timestamp_iso": "2025-09-06T20:19:07.617251+00:00"
}